{
    "master_chef_can": {
        "label": "obj_000001",
        "possible_names": []
    },
    "cracker_box": {
        "label": "obj_000002",
        "possible_names": ["cheezit"]
    },
    "sugar_box": {
        "label": "obj_000003",
        "possible_names": []
    },
    "tomato_soup_can": {
        "label": "obj_000004",
        "possible_names": []
    },
    "mustard_bottle": {
        "label": "obj_000005",
        "possible_names": []
    },
    "tuna_fish_can": {
        "label": "obj_000006",
        "possible_names": []
    },
    "pudding_box": {
        "label": "obj_000007",
        "possible_names": []
    },
    "gelatin_box": {
        "label": "obj_000008",
        "possible_names": []
    },
    "potted_meat_can": {
        "label": "obj_000009",
        "possible_names": []
    },
    "banana": {
        "label": "obj_000010",
        "possible_names": []
    },
    "pitcher_base": {
        "label": "obj_000011",
        "possible_names": []
    },
    "bleach_cleanser": {
        "label": "obj_000012",
        "possible_names": []
    },
    "bowl": {
        "label": "obj_000013",
        "possible_names": []
    },
    "mug": {
        "label": "obj_000014",
        "possible_names": []
    },
    "power_drill": {
        "label": "obj_000015",
        "possible_names": []
    },
    "wood_block": {
        "label": "obj_000016",
        "possible_names": []
    },
    "scissors": {
        "label": "obj_000017",
        "possible_names": []
    },
    "large_marker": {
        "label": "obj_000018",
        "possible_names": []
    },
    "large_clamp": {
        "label": "obj_000019",
        "possible_names": []
    },
    "extra_large_clamp": {
        "label": "obj_000020",
        "possible_names": []
    },
    "foam_brick": {
        "label": "obj_000021",
        "possible_names": []
    }
}
